ddx_ai/__init__.py
ddx_ai/main.py
ddx_ai-0.1.5.dist-info/METADATA
ddx_ai-0.1.5.dist-info/WHEEL
ddx_ai-0.1.5.dist-info/licenses/LICENSE
ddx_ai-0.1.5.dist-info/RECORD
