Metadata-Version: 2.4
Name: ddx-ai
Version: 0.1.5
Summary: DDx is a system to solve complex math problems
Author-email: Diddigam Sai Praneeth <johndoeknown@protonmail.com>
License-File: LICENSE
Requires-Python: >=3.12
Requires-Dist: openai>=1.58.1
Requires-Dist: sympy>=1.13.3
